[
  {
    "incident_id": "1",
    "created_at": "2025-04-05T23:46:53.030Z",
    "status_count": 1,
    "statuses": [
      {
        "shift_id": "2",
        "employee_id": "1",
        "time": "2025-04-05T23:46:53.030Z",
        "description": "Status update for incident 1"
      }
    ]
  },
  {
    "incident_id": "2",
    "created_at": "2025-04-05T23:46:53.030Z",
    "status_count": 1,
    "statuses": [
      {
        "shift_id": "3",
        "employee_id": "2",
        "time": "2025-04-05T23:46:53.030Z",
        "description": "Status update for incident 2"
      }
    ]
  },
  {
    "incident_id": "3",
    "created_at": "2025-04-05T23:46:53.030Z",
    "status_count": 1,
    "statuses": [
      {
        "shift_id": "1",
        "employee_id": "3",
        "time": "2025-04-05T23:46:53.030Z",
        "description": "Status update for incident 3"
      }
    ]
  },
  {
    "incident_id": "4",
    "created_at": "2025-04-05T23:46:53.030Z",
    "status_count": 1,
    "statuses": [
      {
        "shift_id": "2",
        "employee_id": "4",
        "time": "2025-04-05T23:46:53.030Z",
        "description": "Status update for incident 4"
      }
    ]
  },
  {
    "incident_id": "5",
    "created_at": "2025-04-05T23:46:53.030Z",
    "status_count": 1,
    "statuses": [
      {
        "shift_id": "3",
        "employee_id": "5",
        "time": "2025-04-05T23:46:53.030Z",
        "description": "Status update for incident 5"
      }
    ]
  },
  {
    "incident_id": "6",
    "created_at": "2025-04-05T23:46:53.030Z",
    "status_count": 1,
    "statuses": [
      {
        "shift_id": "1",
        "employee_id": "6",
        "time": "2025-04-05T23:46:53.030Z",
        "description": "Status update for incident 6"
      }
    ]
  },
  {
    "incident_id": "7",
    "created_at": "2025-04-05T23:46:53.030Z",
    "status_count": 1,
    "statuses": [
      {
        "shift_id": "2",
        "employee_id": "7",
        "time": "2025-04-05T23:46:53.030Z",
        "description": "Status update for incident 7"
      }
    ]
  },
  {
    "incident_id": "8",
    "created_at": "2025-04-05T23:46:53.030Z",
    "status_count": 1,
    "statuses": [
      {
        "shift_id": "3",
        "employee_id": "8",
        "time": "2025-04-05T23:46:53.030Z",
        "description": "Status update for incident 8"
      }
    ]
  },
  {
    "incident_id": "9",
    "created_at": "2025-04-05T23:46:53.030Z",
    "status_count": 1,
    "statuses": [
      {
        "shift_id": "1",
        "employee_id": "9",
        "time": "2025-04-05T23:46:53.030Z",
        "description": "Status update for incident 9"
      }
    ]
  },
  {
    "incident_id": "10",
    "created_at": "2025-04-05T23:46:53.030Z",
    "status_count": 1,
    "statuses": [
      {
        "shift_id": "2",
        "employee_id": "10",
        "time": "2025-04-05T23:46:53.030Z",
        "description": "Status update for incident 10"
      }
    ]
  },
  {
    "incident_id": "11",
    "created_at": "2025-04-05T23:46:53.030Z",
    "status_count": 1,
    "statuses": [
      {
        "shift_id": "3",
        "employee_id": "11",
        "time": "2025-04-05T23:46:53.030Z",
        "description": "Status update for incident 11"
      }
    ]
  },
  {
    "incident_id": "12",
    "created_at": "2025-04-05T23:46:53.030Z",
    "status_count": 1,
    "statuses": [
      {
        "shift_id": "1",
        "employee_id": "12",
        "time": "2025-04-05T23:46:53.030Z",
        "description": "Status update for incident 12"
      }
    ]
  },
  {
    "incident_id": "13",
    "created_at": "2025-04-05T23:46:53.030Z",
    "status_count": 1,
    "statuses": [
      {
        "shift_id": "2",
        "employee_id": "13",
        "time": "2025-04-05T23:46:53.030Z",
        "description": "Status update for incident 13"
      }
    ]
  },
  {
    "incident_id": "14",
    "created_at": "2025-04-05T23:46:53.030Z",
    "status_count": 1,
    "statuses": [
      {
        "shift_id": "3",
        "employee_id": "14",
        "time": "2025-04-05T23:46:53.030Z",
        "description": "Status update for incident 14"
      }
    ]
  },
  {
    "incident_id": "15",
    "created_at": "2025-04-05T23:46:53.030Z",
    "status_count": 1,
    "statuses": [
      {
        "shift_id": "1",
        "employee_id": "15",
        "time": "2025-04-05T23:46:53.030Z",
        "description": "Status update for incident 15"
      }
    ]
  },
  {
    "incident_id": "16",
    "created_at": "2025-04-05T23:46:53.030Z",
    "status_count": 1,
    "statuses": [
      {
        "shift_id": "2",
        "employee_id": "16",
        "time": "2025-04-05T23:46:53.030Z",
        "description": "Status update for incident 16"
      }
    ]
  },
  {
    "incident_id": "17",
    "created_at": "2025-04-05T23:46:53.030Z",
    "status_count": 1,
    "statuses": [
      {
        "shift_id": "3",
        "employee_id": "17",
        "time": "2025-04-05T23:46:53.030Z",
        "description": "Status update for incident 17"
      }
    ]
  },
  {
    "incident_id": "18",
    "created_at": "2025-04-05T23:46:53.030Z",
    "status_count": 1,
    "statuses": [
      {
        "shift_id": "1",
        "employee_id": "18",
        "time": "2025-04-05T23:46:53.030Z",
        "description": "Status update for incident 18"
      }
    ]
  },
  {
    "incident_id": "19",
    "created_at": "2025-04-05T23:46:53.030Z",
    "status_count": 1,
    "statuses": [
      {
        "shift_id": "2",
        "employee_id": "19",
        "time": "2025-04-05T23:46:53.030Z",
        "description": "Status update for incident 19"
      }
    ]
  },
  {
    "incident_id": "20",
    "created_at": "2025-04-05T23:46:53.030Z",
    "status_count": 1,
    "statuses": [
      {
        "shift_id": "3",
        "employee_id": "20",
        "time": "2025-04-05T23:46:53.030Z",
        "description": "Status update for incident 20"
      }
    ]
  },
  {
    "incident_id": "21",
    "created_at": "2025-04-05T23:46:53.030Z",
    "status_count": 1,
    "statuses": [
      {
        "shift_id": "1",
        "employee_id": "21",
        "time": "2025-04-05T23:46:53.030Z",
        "description": "Status update for incident 21"
      }
    ]
  },
  {
    "incident_id": "22",
    "created_at": "2025-04-05T23:46:53.030Z",
    "status_count": 1,
    "statuses": [
      {
        "shift_id": "2",
        "employee_id": "22",
        "time": "2025-04-05T23:46:53.030Z",
        "description": "Status update for incident 22"
      }
    ]
  },
  {
    "incident_id": "23",
    "created_at": "2025-04-05T23:46:53.030Z",
    "status_count": 1,
    "statuses": [
      {
        "shift_id": "3",
        "employee_id": "23",
        "time": "2025-04-05T23:46:53.030Z",
        "description": "Status update for incident 23"
      }
    ]
  },
  {
    "incident_id": "24",
    "created_at": "2025-04-05T23:46:53.030Z",
    "status_count": 1,
    "statuses": [
      {
        "shift_id": "1",
        "employee_id": "24",
        "time": "2025-04-05T23:46:53.030Z",
        "description": "Status update for incident 24"
      }
    ]
  },
  {
    "incident_id": "25",
    "created_at": "2025-04-05T23:46:53.030Z",
    "status_count": 1,
    "statuses": [
      {
        "shift_id": "2",
        "employee_id": "25",
        "time": "2025-04-05T23:46:53.030Z",
        "description": "Status update for incident 25"
      }
    ]
  },
  {
    "incident_id": "26",
    "created_at": "2025-04-05T23:46:53.030Z",
    "status_count": 1,
    "statuses": [
      {
        "shift_id": "3",
        "employee_id": "26",
        "time": "2025-04-05T23:46:53.030Z",
        "description": "Status update for incident 26"
      }
    ]
  },
  {
    "incident_id": "27",
    "created_at": "2025-04-05T23:46:53.030Z",
    "status_count": 1,
    "statuses": [
      {
        "shift_id": "1",
        "employee_id": "27",
        "time": "2025-04-05T23:46:53.030Z",
        "description": "Status update for incident 27"
      }
    ]
  },
  {
    "incident_id": "28",
    "created_at": "2025-04-05T23:46:53.030Z",
    "status_count": 1,
    "statuses": [
      {
        "shift_id": "2",
        "employee_id": "28",
        "time": "2025-04-05T23:46:53.030Z",
        "description": "Status update for incident 28"
      }
    ]
  },
  {
    "incident_id": "29",
    "created_at": "2025-04-05T23:46:53.030Z",
    "status_count": 1,
    "statuses": [
      {
        "shift_id": "3",
        "employee_id": "29",
        "time": "2025-04-05T23:46:53.030Z",
        "description": "Status update for incident 29"
      }
    ]
  },
  {
    "incident_id": "30",
    "created_at": "2025-04-05T23:46:53.030Z",
    "status_count": 1,
    "statuses": [
      {
        "shift_id": "1",
        "employee_id": "30",
        "time": "2025-04-05T23:46:53.030Z",
        "description": "Status update for incident 30"
      }
    ]
  },
  {
    "incident_id": "31",
    "created_at": "2025-04-05T23:46:53.030Z",
    "status_count": 1,
    "statuses": [
      {
        "shift_id": "2",
        "employee_id": "31",
        "time": "2025-04-05T23:46:53.030Z",
        "description": "Status update for incident 31"
      }
    ]
  },
  {
    "incident_id": "32",
    "created_at": "2025-04-05T23:46:53.030Z",
    "status_count": 1,
    "statuses": [
      {
        "shift_id": "3",
        "employee_id": "32",
        "time": "2025-04-05T23:46:53.030Z",
        "description": "Status update for incident 32"
      }
    ]
  },
  {
    "incident_id": "33",
    "created_at": "2025-04-05T23:46:53.030Z",
    "status_count": 1,
    "statuses": [
      {
        "shift_id": "1",
        "employee_id": "33",
        "time": "2025-04-05T23:46:53.030Z",
        "description": "Status update for incident 33"
      }
    ]
  },
  {
    "incident_id": "34",
    "created_at": "2025-04-05T23:46:53.030Z",
    "status_count": 1,
    "statuses": [
      {
        "shift_id": "2",
        "employee_id": "34",
        "time": "2025-04-05T23:46:53.030Z",
        "description": "Status update for incident 34"
      }
    ]
  },
  {
    "incident_id": "35",
    "created_at": "2025-04-05T23:46:53.030Z",
    "status_count": 1,
    "statuses": [
      {
        "shift_id": "3",
        "employee_id": "35",
        "time": "2025-04-05T23:46:53.030Z",
        "description": "Status update for incident 35"
      }
    ]
  },
  {
    "incident_id": "36",
    "created_at": "2025-04-05T23:46:53.030Z",
    "status_count": 1,
    "statuses": [
      {
        "shift_id": "1",
        "employee_id": "36",
        "time": "2025-04-05T23:46:53.030Z",
        "description": "Status update for incident 36"
      }
    ]
  },
  {
    "incident_id": "37",
    "created_at": "2025-04-05T23:46:53.030Z",
    "status_count": 1,
    "statuses": [
      {
        "shift_id": "2",
        "employee_id": "37",
        "time": "2025-04-05T23:46:53.030Z",
        "description": "Status update for incident 37"
      }
    ]
  },
  {
    "incident_id": "38",
    "created_at": "2025-04-05T23:46:53.030Z",
    "status_count": 1,
    "statuses": [
      {
        "shift_id": "3",
        "employee_id": "38",
        "time": "2025-04-05T23:46:53.030Z",
        "description": "Status update for incident 38"
      }
    ]
  },
  {
    "incident_id": "39",
    "created_at": "2025-04-05T23:46:53.030Z",
    "status_count": 1,
    "statuses": [
      {
        "shift_id": "1",
        "employee_id": "39",
        "time": "2025-04-05T23:46:53.030Z",
        "description": "Status update for incident 39"
      }
    ]
  },
  {
    "incident_id": "40",
    "created_at": "2025-04-05T23:46:53.030Z",
    "status_count": 1,
    "statuses": [
      {
        "shift_id": "2",
        "employee_id": "40",
        "time": "2025-04-05T23:46:53.030Z",
        "description": "Status update for incident 40"
      }
    ]
  },
  {
    "incident_id": "41",
    "created_at": "2025-04-05T23:46:53.030Z",
    "status_count": 1,
    "statuses": [
      {
        "shift_id": "3",
        "employee_id": "41",
        "time": "2025-04-05T23:46:53.030Z",
        "description": "Status update for incident 41"
      }
    ]
  },
  {
    "incident_id": "42",
    "created_at": "2025-04-05T23:46:53.030Z",
    "status_count": 1,
    "statuses": [
      {
        "shift_id": "1",
        "employee_id": "42",
        "time": "2025-04-05T23:46:53.030Z",
        "description": "Status update for incident 42"
      }
    ]
  },
  {
    "incident_id": "43",
    "created_at": "2025-04-05T23:46:53.030Z",
    "status_count": 1,
    "statuses": [
      {
        "shift_id": "2",
        "employee_id": "43",
        "time": "2025-04-05T23:46:53.030Z",
        "description": "Status update for incident 43"
      }
    ]
  },
  {
    "incident_id": "44",
    "created_at": "2025-04-05T23:46:53.030Z",
    "status_count": 1,
    "statuses": [
      {
        "shift_id": "3",
        "employee_id": "44",
        "time": "2025-04-05T23:46:53.030Z",
        "description": "Status update for incident 44"
      }
    ]
  },
  {
    "incident_id": "45",
    "created_at": "2025-04-05T23:46:53.030Z",
    "status_count": 1,
    "statuses": [
      {
        "shift_id": "1",
        "employee_id": "45",
        "time": "2025-04-05T23:46:53.030Z",
        "description": "Status update for incident 45"
      }
    ]
  },
  {
    "incident_id": "46",
    "created_at": "2025-04-05T23:46:53.030Z",
    "status_count": 1,
    "statuses": [
      {
        "shift_id": "2",
        "employee_id": "46",
        "time": "2025-04-05T23:46:53.030Z",
        "description": "Status update for incident 46"
      }
    ]
  },
  {
    "incident_id": "47",
    "created_at": "2025-04-05T23:46:53.030Z",
    "status_count": 1,
    "statuses": [
      {
        "shift_id": "3",
        "employee_id": "47",
        "time": "2025-04-05T23:46:53.030Z",
        "description": "Status update for incident 47"
      }
    ]
  },
  {
    "incident_id": "48",
    "created_at": "2025-04-05T23:46:53.030Z",
    "status_count": 1,
    "statuses": [
      {
        "shift_id": "1",
        "employee_id": "48",
        "time": "2025-04-05T23:46:53.030Z",
        "description": "Status update for incident 48"
      }
    ]
  },
  {
    "incident_id": "49",
    "created_at": "2025-04-05T23:46:53.030Z",
    "status_count": 1,
    "statuses": [
      {
        "shift_id": "2",
        "employee_id": "49",
        "time": "2025-04-05T23:46:53.030Z",
        "description": "Status update for incident 49"
      }
    ]
  },
  {
    "incident_id": "50",
    "created_at": "2025-04-05T23:46:53.030Z",
    "status_count": 1,
    "statuses": [
      {
        "shift_id": "3",
        "employee_id": "50",
        "time": "2025-04-05T23:46:53.030Z",
        "description": "Status update for incident 50"
      }
    ]
  },
  {
    "incident_id": "51",
    "created_at": "2025-04-05T23:46:53.030Z",
    "status_count": 1,
    "statuses": [
      {
        "shift_id": "1",
        "employee_id": "51",
        "time": "2025-04-05T23:46:53.030Z",
        "description": "Status update for incident 51"
      }
    ]
  },
  {
    "incident_id": "52",
    "created_at": "2025-04-05T23:46:53.030Z",
    "status_count": 1,
    "statuses": [
      {
        "shift_id": "2",
        "employee_id": "52",
        "time": "2025-04-05T23:46:53.030Z",
        "description": "Status update for incident 52"
      }
    ]
  },
  {
    "incident_id": "53",
    "created_at": "2025-04-05T23:46:53.030Z",
    "status_count": 1,
    "statuses": [
      {
        "shift_id": "3",
        "employee_id": "53",
        "time": "2025-04-05T23:46:53.030Z",
        "description": "Status update for incident 53"
      }
    ]
  },
  {
    "incident_id": "54",
    "created_at": "2025-04-05T23:46:53.030Z",
    "status_count": 1,
    "statuses": [
      {
        "shift_id": "1",
        "employee_id": "54",
        "time": "2025-04-05T23:46:53.030Z",
        "description": "Status update for incident 54"
      }
    ]
  },
  {
    "incident_id": "55",
    "created_at": "2025-04-05T23:46:53.030Z",
    "status_count": 1,
    "statuses": [
      {
        "shift_id": "2",
        "employee_id": "55",
        "time": "2025-04-05T23:46:53.030Z",
        "description": "Status update for incident 55"
      }
    ]
  },
  {
    "incident_id": "56",
    "created_at": "2025-04-05T23:46:53.030Z",
    "status_count": 1,
    "statuses": [
      {
        "shift_id": "3",
        "employee_id": "56",
        "time": "2025-04-05T23:46:53.030Z",
        "description": "Status update for incident 56"
      }
    ]
  },
  {
    "incident_id": "57",
    "created_at": "2025-04-05T23:46:53.030Z",
    "status_count": 1,
    "statuses": [
      {
        "shift_id": "1",
        "employee_id": "57",
        "time": "2025-04-05T23:46:53.030Z",
        "description": "Status update for incident 57"
      }
    ]
  },
  {
    "incident_id": "58",
    "created_at": "2025-04-05T23:46:53.030Z",
    "status_count": 1,
    "statuses": [
      {
        "shift_id": "2",
        "employee_id": "58",
        "time": "2025-04-05T23:46:53.030Z",
        "description": "Status update for incident 58"
      }
    ]
  },
  {
    "incident_id": "59",
    "created_at": "2025-04-05T23:46:53.030Z",
    "status_count": 1,
    "statuses": [
      {
        "shift_id": "3",
        "employee_id": "59",
        "time": "2025-04-05T23:46:53.030Z",
        "description": "Status update for incident 59"
      }
    ]
  },
  {
    "incident_id": "60",
    "created_at": "2025-04-05T23:46:53.030Z",
    "status_count": 1,
    "statuses": [
      {
        "shift_id": "1",
        "employee_id": "60",
        "time": "2025-04-05T23:46:53.030Z",
        "description": "Status update for incident 60"
      }
    ]
  },
  {
    "incident_id": "61",
    "created_at": "2025-04-05T23:46:53.030Z",
    "status_count": 1,
    "statuses": [
      {
        "shift_id": "2",
        "employee_id": "61",
        "time": "2025-04-05T23:46:53.030Z",
        "description": "Status update for incident 61"
      }
    ]
  },
  {
    "incident_id": "62",
    "created_at": "2025-04-05T23:46:53.030Z",
    "status_count": 1,
    "statuses": [
      {
        "shift_id": "3",
        "employee_id": "62",
        "time": "2025-04-05T23:46:53.030Z",
        "description": "Status update for incident 62"
      }
    ]
  },
  {
    "incident_id": "63",
    "created_at": "2025-04-05T23:46:53.030Z",
    "status_count": 1,
    "statuses": [
      {
        "shift_id": "1",
        "employee_id": "63",
        "time": "2025-04-05T23:46:53.030Z",
        "description": "Status update for incident 63"
      }
    ]
  },
  {
    "incident_id": "64",
    "created_at": "2025-04-05T23:46:53.030Z",
    "status_count": 1,
    "statuses": [
      {
        "shift_id": "2",
        "employee_id": "64",
        "time": "2025-04-05T23:46:53.030Z",
        "description": "Status update for incident 64"
      }
    ]
  },
  {
    "incident_id": "65",
    "created_at": "2025-04-05T23:46:53.030Z",
    "status_count": 1,
    "statuses": [
      {
        "shift_id": "3",
        "employee_id": "65",
        "time": "2025-04-05T23:46:53.030Z",
        "description": "Status update for incident 65"
      }
    ]
  },
  {
    "incident_id": "66",
    "created_at": "2025-04-05T23:46:53.030Z",
    "status_count": 1,
    "statuses": [
      {
        "shift_id": "1",
        "employee_id": "66",
        "time": "2025-04-05T23:46:53.030Z",
        "description": "Status update for incident 66"
      }
    ]
  },
  {
    "incident_id": "67",
    "created_at": "2025-04-05T23:46:53.030Z",
    "status_count": 1,
    "statuses": [
      {
        "shift_id": "2",
        "employee_id": "67",
        "time": "2025-04-05T23:46:53.030Z",
        "description": "Status update for incident 67"
      }
    ]
  },
  {
    "incident_id": "68",
    "created_at": "2025-04-05T23:46:53.030Z",
    "status_count": 1,
    "statuses": [
      {
        "shift_id": "3",
        "employee_id": "68",
        "time": "2025-04-05T23:46:53.030Z",
        "description": "Status update for incident 68"
      }
    ]
  },
  {
    "incident_id": "69",
    "created_at": "2025-04-05T23:46:53.030Z",
    "status_count": 1,
    "statuses": [
      {
        "shift_id": "1",
        "employee_id": "69",
        "time": "2025-04-05T23:46:53.030Z",
        "description": "Status update for incident 69"
      }
    ]
  },
  {
    "incident_id": "70",
    "created_at": "2025-04-05T23:46:53.030Z",
    "status_count": 1,
    "statuses": [
      {
        "shift_id": "2",
        "employee_id": "70",
        "time": "2025-04-05T23:46:53.030Z",
        "description": "Status update for incident 70"
      }
    ]
  },
  {
    "incident_id": "71",
    "created_at": "2025-04-05T23:46:53.030Z",
    "status_count": 1,
    "statuses": [
      {
        "shift_id": "3",
        "employee_id": "71",
        "time": "2025-04-05T23:46:53.030Z",
        "description": "Status update for incident 71"
      }
    ]
  },
  {
    "incident_id": "72",
    "created_at": "2025-04-05T23:46:53.030Z",
    "status_count": 1,
    "statuses": [
      {
        "shift_id": "1",
        "employee_id": "72",
        "time": "2025-04-05T23:46:53.030Z",
        "description": "Status update for incident 72"
      }
    ]
  },
  {
    "incident_id": "73",
    "created_at": "2025-04-05T23:46:53.030Z",
    "status_count": 1,
    "statuses": [
      {
        "shift_id": "2",
        "employee_id": "73",
        "time": "2025-04-05T23:46:53.030Z",
        "description": "Status update for incident 73"
      }
    ]
  },
  {
    "incident_id": "74",
    "created_at": "2025-04-05T23:46:53.030Z",
    "status_count": 1,
    "statuses": [
      {
        "shift_id": "3",
        "employee_id": "74",
        "time": "2025-04-05T23:46:53.030Z",
        "description": "Status update for incident 74"
      }
    ]
  },
  {
    "incident_id": "75",
    "created_at": "2025-04-05T23:46:53.030Z",
    "status_count": 1,
    "statuses": [
      {
        "shift_id": "1",
        "employee_id": "75",
        "time": "2025-04-05T23:46:53.030Z",
        "description": "Status update for incident 75"
      }
    ]
  },
  {
    "incident_id": "76",
    "created_at": "2025-04-05T23:46:53.030Z",
    "status_count": 1,
    "statuses": [
      {
        "shift_id": "2",
        "employee_id": "76",
        "time": "2025-04-05T23:46:53.030Z",
        "description": "Status update for incident 76"
      }
    ]
  },
  {
    "incident_id": "77",
    "created_at": "2025-04-05T23:46:53.030Z",
    "status_count": 1,
    "statuses": [
      {
        "shift_id": "3",
        "employee_id": "77",
        "time": "2025-04-05T23:46:53.030Z",
        "description": "Status update for incident 77"
      }
    ]
  },
  {
    "incident_id": "78",
    "created_at": "2025-04-05T23:46:53.030Z",
    "status_count": 1,
    "statuses": [
      {
        "shift_id": "1",
        "employee_id": "78",
        "time": "2025-04-05T23:46:53.030Z",
        "description": "Status update for incident 78"
      }
    ]
  },
  {
    "incident_id": "79",
    "created_at": "2025-04-05T23:46:53.030Z",
    "status_count": 1,
    "statuses": [
      {
        "shift_id": "2",
        "employee_id": "79",
        "time": "2025-04-05T23:46:53.030Z",
        "description": "Status update for incident 79"
      }
    ]
  },
  {
    "incident_id": "80",
    "created_at": "2025-04-05T23:46:53.030Z",
    "status_count": 1,
    "statuses": [
      {
        "shift_id": "3",
        "employee_id": "80",
        "time": "2025-04-05T23:46:53.030Z",
        "description": "Status update for incident 80"
      }
    ]
  },
  {
    "incident_id": "81",
    "created_at": "2025-04-05T23:46:53.030Z",
    "status_count": 1,
    "statuses": [
      {
        "shift_id": "1",
        "employee_id": "81",
        "time": "2025-04-05T23:46:53.030Z",
        "description": "Status update for incident 81"
      }
    ]
  },
  {
    "incident_id": "82",
    "created_at": "2025-04-05T23:46:53.030Z",
    "status_count": 1,
    "statuses": [
      {
        "shift_id": "2",
        "employee_id": "82",
        "time": "2025-04-05T23:46:53.030Z",
        "description": "Status update for incident 82"
      }
    ]
  },
  {
    "incident_id": "83",
    "created_at": "2025-04-05T23:46:53.030Z",
    "status_count": 1,
    "statuses": [
      {
        "shift_id": "3",
        "employee_id": "83",
        "time": "2025-04-05T23:46:53.030Z",
        "description": "Status update for incident 83"
      }
    ]
  },
  {
    "incident_id": "84",
    "created_at": "2025-04-05T23:46:53.030Z",
    "status_count": 1,
    "statuses": [
      {
        "shift_id": "1",
        "employee_id": "84",
        "time": "2025-04-05T23:46:53.030Z",
        "description": "Status update for incident 84"
      }
    ]
  },
  {
    "incident_id": "85",
    "created_at": "2025-04-05T23:46:53.030Z",
    "status_count": 1,
    "statuses": [
      {
        "shift_id": "2",
        "employee_id": "85",
        "time": "2025-04-05T23:46:53.030Z",
        "description": "Status update for incident 85"
      }
    ]
  },
  {
    "incident_id": "86",
    "created_at": "2025-04-05T23:46:53.030Z",
    "status_count": 1,
    "statuses": [
      {
        "shift_id": "3",
        "employee_id": "86",
        "time": "2025-04-05T23:46:53.030Z",
        "description": "Status update for incident 86"
      }
    ]
  },
  {
    "incident_id": "87",
    "created_at": "2025-04-05T23:46:53.030Z",
    "status_count": 1,
    "statuses": [
      {
        "shift_id": "1",
        "employee_id": "87",
        "time": "2025-04-05T23:46:53.030Z",
        "description": "Status update for incident 87"
      }
    ]
  },
  {
    "incident_id": "88",
    "created_at": "2025-04-05T23:46:53.030Z",
    "status_count": 1,
    "statuses": [
      {
        "shift_id": "2",
        "employee_id": "88",
        "time": "2025-04-05T23:46:53.030Z",
        "description": "Status update for incident 88"
      }
    ]
  },
  {
    "incident_id": "89",
    "created_at": "2025-04-05T23:46:53.030Z",
    "status_count": 1,
    "statuses": [
      {
        "shift_id": "3",
        "employee_id": "89",
        "time": "2025-04-05T23:46:53.030Z",
        "description": "Status update for incident 89"
      }
    ]
  },
  {
    "incident_id": "90",
    "created_at": "2025-04-05T23:46:53.030Z",
    "status_count": 1,
    "statuses": [
      {
        "shift_id": "1",
        "employee_id": "90",
        "time": "2025-04-05T23:46:53.030Z",
        "description": "Status update for incident 90"
      }
    ]
  },
  {
    "incident_id": "91",
    "created_at": "2025-04-05T23:46:53.030Z",
    "status_count": 1,
    "statuses": [
      {
        "shift_id": "2",
        "employee_id": "91",
        "time": "2025-04-05T23:46:53.030Z",
        "description": "Status update for incident 91"
      }
    ]
  },
  {
    "incident_id": "92",
    "created_at": "2025-04-05T23:46:53.030Z",
    "status_count": 1,
    "statuses": [
      {
        "shift_id": "3",
        "employee_id": "92",
        "time": "2025-04-05T23:46:53.030Z",
        "description": "Status update for incident 92"
      }
    ]
  },
  {
    "incident_id": "93",
    "created_at": "2025-04-05T23:46:53.030Z",
    "status_count": 1,
    "statuses": [
      {
        "shift_id": "1",
        "employee_id": "93",
        "time": "2025-04-05T23:46:53.030Z",
        "description": "Status update for incident 93"
      }
    ]
  },
  {
    "incident_id": "94",
    "created_at": "2025-04-05T23:46:53.030Z",
    "status_count": 1,
    "statuses": [
      {
        "shift_id": "2",
        "employee_id": "94",
        "time": "2025-04-05T23:46:53.030Z",
        "description": "Status update for incident 94"
      }
    ]
  },
  {
    "incident_id": "95",
    "created_at": "2025-04-05T23:46:53.030Z",
    "status_count": 1,
    "statuses": [
      {
        "shift_id": "3",
        "employee_id": "95",
        "time": "2025-04-05T23:46:53.030Z",
        "description": "Status update for incident 95"
      }
    ]
  },
  {
    "incident_id": "96",
    "created_at": "2025-04-05T23:46:53.030Z",
    "status_count": 1,
    "statuses": [
      {
        "shift_id": "1",
        "employee_id": "96",
        "time": "2025-04-05T23:46:53.030Z",
        "description": "Status update for incident 96"
      }
    ]
  },
  {
    "incident_id": "97",
    "created_at": "2025-04-05T23:46:53.030Z",
    "status_count": 1,
    "statuses": [
      {
        "shift_id": "2",
        "employee_id": "97",
        "time": "2025-04-05T23:46:53.030Z",
        "description": "Status update for incident 97"
      }
    ]
  },
  {
    "incident_id": "98",
    "created_at": "2025-04-05T23:46:53.030Z",
    "status_count": 1,
    "statuses": [
      {
        "shift_id": "3",
        "employee_id": "98",
        "time": "2025-04-05T23:46:53.030Z",
        "description": "Status update for incident 98"
      }
    ]
  },
  {
    "incident_id": "99",
    "created_at": "2025-04-05T23:46:53.030Z",
    "status_count": 1,
    "statuses": [
      {
        "shift_id": "1",
        "employee_id": "99",
        "time": "2025-04-05T23:46:53.030Z",
        "description": "Status update for incident 99"
      }
    ]
  },
  {
    "incident_id": "100",
    "created_at": "2025-04-05T23:46:53.030Z",
    "status_count": 1,
    "statuses": [
      {
        "shift_id": "2",
        "employee_id": "100",
        "time": "2025-04-05T23:46:53.030Z",
        "description": "Status update for incident 100"
      }
    ]
  },
  {
    "incident_id": "101",
    "created_at": "2024-01-01T10:30:00.000Z",
    "status_count": 2,
    "statuses": [
      {
        "shift_id": "1",
        "employee_id": "1",
        "time": "2024-01-01T10:30:00.000Z",
        "description": "Rozpoczęto diagnostykę"
      },
      {
        "shift_id": "2",
        "employee_id": "2",
        "time": "2024-01-01T16:30:00.000Z",
        "description": "Wymieniono dysk"
      }
    ]
  },
  {
    "incident_id": "102",
    "created_at": "2024-01-01T20:30:00.000Z",
    "status_count": 2,
    "statuses": [
      {
        "shift_id": "2",
        "employee_id": "2",
        "time": "2024-01-01T20:30:00.000Z",
        "description": "Zgłoszono problem"
      },
      {
        "shift_id": "3",
        "employee_id": "3",
        "time": "2024-01-02T01:00:00.000Z",
        "description": "Wymiana matrycy w toku"
      }
    ]
  },
  {
    "incident_id": "103",
    "created_at": "2024-01-01T12:30:00.000Z",
    "status_count": 3,
    "statuses": [
      {
        "shift_id": "1",
        "employee_id": "1",
        "time": "2024-01-01T12:30:00.000Z",
        "description": "Awaria zgłoszona"
      },
      {
        "shift_id": "2",
        "employee_id": "2",
        "time": "2024-01-01T18:00:00.000Z",
        "description": "Sprawdzanie zasilacza"
      },
      {
        "shift_id": "3",
        "employee_id": "3",
        "time": "2024-01-02T03:00:00.000Z",
        "description": "Wymiana zasilacza"
      }
    ]
  },
  {
    "incident_id": "104",
    "created_at": "2024-01-01T09:00:00.000Z",
    "status_count": 3,
    "statuses": [
      {
        "shift_id": "1",
        "employee_id": "1",
        "time": "2024-01-01T09:00:00.000Z",
        "description": "Rozpoczęcie diagnozy"
      },
      {
        "shift_id": "2",
        "employee_id": "2",
        "time": "2024-01-02T14:00:00.000Z",
        "description": "Zamówiono części"
      },
      {
        "shift_id": "3",
        "employee_id": "3",
        "time": "2024-01-03T16:00:00.000Z",
        "description": "Naprawa zakończona"
      }
    ]
  },
  {
    "incident_id": "105",
    "created_at": "2024-01-02T11:00:00.000Z",
    "status_count": 3,
    "statuses": [
      {
        "shift_id": "2",
        "employee_id": "2",
        "time": "2024-01-02T11:00:00.000Z",
        "description": "Zgłoszenie przyjęte"
      },
      {
        "shift_id": "3",
        "employee_id": "3",
        "time": "2024-01-04T10:00:00.000Z",
        "description": "Wymiana w toku"
      },
      {
        "shift_id": "1",
        "employee_id": "1",
        "time": "2024-01-05T14:00:00.000Z",
        "description": "Testowanie po naprawie"
      }
    ]
  },
  {
    "incident_id": "106",
    "created_at": "2024-01-04T10:00:00.000Z",
    "status_count": 3,
    "statuses": [
      {
        "shift_id": "3",
        "employee_id": "3",
        "time": "2024-01-04T10:00:00.000Z",
        "description": "Początek prac"
      },
      {
        "shift_id": "1",
        "employee_id": "1",
        "time": "2024-01-06T11:00:00.000Z",
        "description": "Diagnoza dysku"
      },
      {
        "shift_id": "2",
        "employee_id": "2",
        "time": "2024-01-08T15:00:00.000Z",
        "description": "Naprawa zakończona"
      }
    ]
  },
  {
    "incident_id": "107",
    "created_at": "2024-01-05T10:00:00.000Z",
    "status_count": 3,
    "statuses": [
      {
        "shift_id": "3",
        "employee_id": "3",
        "time": "2024-01-05T10:00:00.000Z",
        "description": "Początek prac"
      },
      {
        "shift_id": "1",
        "employee_id": "1",
        "time": "2024-01-05T11:00:00.000Z",
        "description": "Połączenie z siecią"
      },
      {
        "shift_id": "2",
        "employee_id": "2",
        "time": "2024-01-06T15:00:00.000Z",
        "description": "Naprawa zakończona"
      }
    ]
  }
]